taizmath
